{"id": 1292, "links": ["https://legis.senado.leg.br/sdleg-getter/documento/download/cf58aac0-b178-4829-a2f6-08d082ebd7a0"], "data_recebimento": "30/06/2021", "remetente": "STF - Supremo Tribunal Federal", "origem": "\nOf\u00edcio n\u00ba 1539/2021\n28/06/2021\n", "descricao": "\nDefere liminar para determinar suspen\u00e7\u00e3o de delibera\u00e7\u00e3o de quebra de sigilos banc\u00e1rio, fiscal e telem\u00e1tico em Medida Cautelar em Mandado de Seguran\u00e7a n\u00ba 38006, impetrado por CALIA/ Y2 PROPAGANDA E MARKETING LTDA.\n\n\t\t\t\t\t\t\tDocumenta\u00e7\u00e3o contendo:\n\t\t\t\t\t\t\t\n\t\t\t\t\t\t\t618 folha(s).\n\t\t\t\t\t\t\t\n", "caixa": " 0   ", "em_resposta": " 0   "}