{"id": 1641, "links": ["https://legis.senado.leg.br/sdleg-getter/documento/download/8cb53da8-3663-4ccd-96f7-9b44ae00801f", "https://legis.senado.leg.br/sdleg-getter/documento/download/40425ab8-2645-4fa0-a9c6-15132d0d2025"], "data_recebimento": "09/07/2021", "remetente": "Governo do Estado do Cear\u00e1", "origem": "\nOF\u00cdCIO GG N\u00ba 265 / 2021\n08/07/2021\n", "descricao": "\nSolicita prazo adicional de 30 dis \u00fateis.\n\n\t\t\t\t\t\t\tDocumenta\u00e7\u00e3o contendo:\n\t\t\t\t\t\t\t\n\t\t\t\t\t\t\t folha(s).\n\t\t\t\t\t\t\t\n", "caixa": " 0   ", "em_resposta": " 0   "}