{"id": 1879, "links": ["https://legis.senado.leg.br/sdleg-getter/documento/download/c7c06023-d3ce-4db1-83d1-1110754ae7fd", "https://legis.senado.leg.br/sdleg-getter/documento/download/850e33aa-796c-4ac9-b662-3ff284de657f"], "data_recebimento": "20/07/2021", "remetente": "Prefeitura de Campinas", "origem": "\nOf\u00edcio n.\u00ba 179/2021 - Gabinete do Prefeito\n19/07/2021\n", "descricao": "\nEncaminha as informa\u00e7\u00f5es complementares prestadas pelas Secretarias Municipais de Sa\u00fade, Gest\u00e3o e Controle e Assist\u00eancia Social.\n\n\t\t\t\t\t\t\tDocumenta\u00e7\u00e3o contendo:\n\t\t\t\t\t\t\t\n\t\t\t\t\t\t\t0 folha(s).\n\t\t\t\t\t\t\t\n", "caixa": " 0   ", "em_resposta": " 0   "}