{"id": 506, "links": ["https://legis.senado.leg.br/sdleg-getter/documento/download/85b37085-b227-4835-a094-74c324726ea2"], "data_recebimento": "26/05/2021", "remetente": "Governo do Estado de S\u00e3o Paulo", "origem": "\nOf\u00edcio GS n\u00ba 1399/2021\n14/05/2021\n", "descricao": "\nEncaminha respostas aos Of\u00edcios 929/2021, 717/2021 e 985/2021\n\n\t\t\t\t\t\t\tDocumenta\u00e7\u00e3o contendo:\n\t\t\t\t\t\t\t\n\t\t\t\t\t\t\t3 folha(s).\n\t\t\t\t\t\t\t\n", "caixa": " 1   ", "em_resposta": " 1   "}