{"id": 973, "links": ["https://legis.senado.leg.br/sdleg-getter/documento/download/c91b3284-4766-44ea-b30b-a64d5fb700a1", "https://legis.senado.leg.br/sdleg-getter/documento/download/37debe47-26d4-4ec9-a8dc-60a3bbbf96fd"], "data_recebimento": "16/06/2021", "remetente": "MRE - Minist\u00e9rio das  Rela\u00e7\u00f5es  Exteriores", "origem": "\nOf\u00edcio n\u00ba 09054.000473/2021-99\n15/06/2021\n", "descricao": "\nEncaminha Nota Jur\u00eddica n. 00005/2021/GABCONJUR/CONJUR-MRE/CGU/AGU e pede sua juntada ao anexo do Of\u00edcio n\u00ba 35 G/SG/AFEPA, que apresentou considera\u00e7\u00f5es quanto ao Requerimento n\u00ba 781/2021, de reclassifica\u00e7\u00e3o de documentos desta CPI. [Complementa\u00e7\u00e3o ao DOC 965].\n\n\t\t\t\t\t\t\tDocumenta\u00e7\u00e3o contendo:\n\t\t\t\t\t\t\t\n\t\t\t\t\t\t\t10 folha(s).\n\t\t\t\t\t\t\t\n", "caixa": " 1   ", "em_resposta": " 1   "}