{"id": 990, "links": ["https://legis.senado.leg.br/sdleg-getter/documento/download/4caf3104-5a24-4e32-bb0d-f6c05d9bd6bd"], "data_recebimento": "17/06/2021", "remetente": "Procuradoria da Rep\u00fablica - Amap\u00e1", "origem": "\nDespacho n\u00ba 3764/2021\n16/06/2021\n", "descricao": "\nDespacho da Procuradoria da Rep\u00fablica no Amap\u00e1, informando que, em rela\u00e7\u00e3o \u00e0 Opera\u00e7\u00e3o Tendas de Ouro, h\u00e1 medidas cautelares judicialmente deferidas e que permanecem sob sigilo, do qual n\u00e3o cabe ao MPF dispor.\n\n\t\t\t\t\t\t\tDocumenta\u00e7\u00e3o contendo:\n\t\t\t\t\t\t\t\n\t\t\t\t\t\t\t5 folha(s).\n\t\t\t\t\t\t\t\n", "caixa": " 1   ", "em_resposta": " 1   "}